drf_simple_invite/__init__.py
drf_simple_invite/admin.py
drf_simple_invite/apps.py
drf_simple_invite/models.py
drf_simple_invite/serializers.py
drf_simple_invite/signals.py
drf_simple_invite/urls.py
drf_simple_invite/views.py
drf_simple_invite/migrations/0001_initial.py
drf_simple_invite/migrations/__init__.py
drf_simple_invite-0.3.0.dist-info/LICENSE
drf_simple_invite-0.3.0.dist-info/METADATA
drf_simple_invite-0.3.0.dist-info/WHEEL
drf_simple_invite-0.3.0.dist-info/top_level.txt
drf_simple_invite-0.3.0.dist-info/RECORD
