Metadata-Version: 2.1
Name: drf_simple_invite
Version: 0.3.0
Summary: An extension of django rest framework that allows to invite user via email
Home-page: https://github.com/thapabishwa/drf-simple-invite/
Author: Bishwa Thapa
Author-email: thapabishwa@aol.com
License: BSD License
Classifier: Development Status :: 4 - Beta
Classifier: Environment :: Web Environment
Classifier: Framework :: Django :: 2.0
Classifier: Framework :: Django :: 2.1
Classifier: Intended Audience :: Developers
Classifier: License :: OSI Approved :: BSD License
Classifier: Operating System :: OS Independent
Classifier: Programming Language :: Python
Classifier: Programming Language :: Python :: 3.4
Classifier: Programming Language :: Python :: 3.5
Classifier: Programming Language :: Python :: 3.6
Classifier: Topic :: Internet :: WWW/HTTP
Classifier: Topic :: Internet :: WWW/HTTP :: Dynamic Content
License-File: LICENSE
